milmapcon/__init__.py
milmapcon/gs_data.db
milmapcon/milmapcon.py
milmapcon-1.0.2.dist-info/LICENSE.txt
milmapcon-1.0.2.dist-info/METADATA
milmapcon-1.0.2.dist-info/WHEEL
milmapcon-1.0.2.dist-info/top_level.txt
milmapcon-1.0.2.dist-info/RECORD
