Metadata-Version: 2.2
Name: milmapcon
Version: 1.0.2
Summary: A coordinate converter built on pyproj to convert WWII-era map grid coordinates to latitude & longitude
Home-page: https://github.com/mkershis/milmapcon
Author: Matt Kershis
License: MIT License
Project-URL: Homepage, https://github.com/mkershis/milmapcon
Project-URL: Issues, https://github.com/mkershis/milmapcon/issues
Classifier: Programming Language :: Python :: 3.11
Classifier: Operating System :: OS Independent
Requires-Python: >=3.11.7
License-File: LICENSE.txt
Requires-Dist: pyproj>=3.6.1
Requires-Dist: certifi>=2024.12.14
Requires-Dist: pathlib>=1.0.1
Dynamic: home-page
Dynamic: requires-python
